{
  "name": "colors",
  "description": "get colors in your node.js console",
  "dist-tags": {
    "latest": "1.3.3",
    "next": "1.2.0-rc0"
  },
  "versions": [
    "0.3.0",
    "0.5.0",
    "0.5.1",
    "0.6.0-1",
    "0.6.0",
    "0.6.1",
    "0.6.2",
    "1.0.0",
    "1.0.1",
    "1.0.2",
    "1.0.3",
    "1.1.0",
    "1.1.1",
    "1.1.2",
    "1.2.0-rc0",
    "1.2.0",
    "1.2.1",
    "1.2.2",
    "1.2.3",
    "1.2.4",
    "1.2.5",
    "1.3.0",
    "1.3.1",
    "1.3.2",
    "1.3.3"
  ],
  "maintainers": [
    "dabh <dabh@stanford.edu>",
    "marak <marak.squires@gmail.com>"
  ],
  "author": "Marak Squires",
  "repository": {
    "type": "git",
    "url": "git+ssh://git@github.com/Marak/colors.js.git"
  },
  "time": {
    "modified": "2019-07-25T07:59:01.865Z",
    "created": "2011-03-15T10:12:18.245Z",
    "0.3.0": "2011-03-15T10:12:18.245Z",
    "0.5.0": "2011-03-15T10:12:18.245Z",
    "0.5.1": "2011-09-25T13:04:44.328Z",
    "0.6.0": "2011-12-09T11:32:57.649Z",
    "0.6.0-1": "2011-12-09T12:35:05.501Z",
    "0.6.1": "2013-07-26T05:49:48.513Z",
    "0.6.2": "2013-08-21T23:14:55.906Z",
    "1.0.0": "2014-10-01T11:29:39.467Z",
    "1.0.1": "2014-10-01T16:07:39.787Z",
    "1.0.2": "2014-10-02T19:55:43.478Z",
    "1.0.3": "2014-10-09T10:03:24.510Z",
    "1.1.0": "2015-04-29T07:15:49.571Z",
    "1.1.1": "2015-06-17T12:52:33.681Z",
    "1.1.2": "2015-06-17T13:03:00.583Z",
    "1.2.0-rc0": "2018-02-16T22:45:09.148Z",
    "1.2.0": "2018-03-10T06:48:40.310Z",
    "1.2.1": "2018-03-12T05:52:26.861Z",
    "1.2.2": "2018-04-30T18:42:10.848Z",
    "1.2.3": "2018-04-30T22:09:46.566Z",
    "1.2.4": "2018-05-05T00:56:06.245Z",
    "1.2.5": "2018-05-11T06:15:42.549Z",
    "1.3.0": "2018-05-20T22:09:35.759Z",
    "1.3.1": "2018-07-22T22:06:27.574Z",
    "1.3.2": "2018-08-22T18:48:50.238Z",
    "1.3.3": "2018-12-10T01:35:48.987Z"
  },
  "users": {
    "avianflu": true,
    "pid": true,
    "vasc": true,
    "dodo": true,
    "matthiasg": true,
    "kevinohara80": true,
    "blakmatrix": true,
    "fgribreau": true,
    "kennethjor": true,
    "divanvisagie": true,
    "megadrive": true,
    "evanlucas": true,
    "dbrockman": true,
    "eins78": true,
    "maxmaximov": true,
    "zonetti": true,
    "leesei": true,
    "paulj": true,
    "cmilhench": true,
    "chilts": true,
    "moonpyk": true,
    "victorquinn": true,
    "lexa": true,
    "making3": true,
    "suziam": true,
    "tigefa": true,
    "pana": true,
    "spekkionu": true,
    "simon.turvey": true,
    "noopkat": true,
    "jonathanmelville": true,
    "phette23": true,
    "putaoshu": true,
    "timur.shemsedinov": true,
    "ettalea": true,
    "jacques": true,
    "jasonwbsg": true,
    "alivesay": true,
    "tengisb": true,
    "apache2046": true,
    "cilindrox": true,
    "tarcio": true,
    "kerry95": true,
    "davidwbradford": true,
    "funroll": true,
    "newblt123": true,
    "starak": true,
    "cocopas": true,
    "magemagic": true,
    "ubi": true,
    "andydrew": true,
    "morishitter": true,
    "dimoreira": true,
    "fanchangyong": true,
    "jimnox": true,
    "wentworthzheng": true,
    "humantriangle": true,
    "bengarrett": true,
    "chrisyboy53": true,
    "zeusdeux": true,
    "owaz": true,
    "shen-weizhong": true,
    "scriptnull": true,
    "chaowi": true,
    "seldo": true,
    "edalorzo": true,
    "afollestad": true,
    "davidrlee": true,
    "davidchase": true,
    "steel1990": true,
    "jokarlist": true,
    "tchey": true,
    "binnng": true,
    "dercoder": true,
    "dofy": true,
    "tjwebb": true,
    "vancarney": true,
    "mswanson1524": true,
    "inderdeep": true,
    "blakedietz": true,
    "fill": true,
    "wlfyit": true,
    "jits": true,
    "stonecypher": true,
    "riaanpelser": true,
    "karmadude": true,
    "formix": true,
    "brentonhouse": true,
    "rpgreen": true,
    "itonyyo": true,
    "momepukku": true,
    "yourhoneysky": true,
    "spielberg": true,
    "gliviu": true,
    "rosterloh": true,
    "ali1k": true,
    "l0n9h02n": true,
    "dominik.palo": true,
    "coachshea": true,
    "congcong": true,
    "icaliman": true,
    "ivangaravito": true,
    "mastayoda": true,
    "ziehlke": true,
    "thorsson": true,
    "gayan": true,
    "ashkyd": true,
    "kaiquewdev": true,
    "flyslow": true,
    "stpettersens": true,
    "vrfrnco": true,
    "jsolis": true,
    "trevin": true,
    "f124275809": true,
    "lazycoder": true,
    "aitorllj93": true,
    "frknbasaran": true,
    "wangnan0610": true,
    "hellocodeming": true,
    "sametsisartenep": true,
    "streamer": true,
    "hellgrenj": true,
    "haeck": true,
    "jcottam": true,
    "otaviolms": true,
    "mykhael": true,
    "mpcref": true,
    "iksnae": true,
    "r3nya": true,
    "kulakowka": true,
    "justintormey": true,
    "skyinlayer": true,
    "alejcerro": true,
    "hootping": true,
    "sexyoung1985": true,
    "pnevares": true,
    "fabianbach": true,
    "barenko": true,
    "joaocunha": true,
    "adammacias": true,
    "semencov": true,
    "phoward8020": true,
    "j3kz": true,
    "michaelchance": true,
    "rbartoli": true,
    "yashprit": true,
    "jun01ito": true,
    "kankungyip": true,
    "cbpetersen": true,
    "rcastro": true,
    "onofremartins": true,
    "viztor": true,
    "tmcguire": true,
    "qqqppp9998": true,
    "f2enav": true,
    "dolymood": true,
    "jonatasnona": true,
    "sanketss84": true,
    "tonydieu": true,
    "rosshal": true,
    "jesusgoku": true,
    "ezcabrera": true,
    "xxronis": true,
    "buzuli": true,
    "smd4": true,
    "rbecheras": true,
    "drewnull": true,
    "dennisgnl": true,
    "shriek": true,
    "nukisman": true,
    "incendiary": true,
    "huacnlee": true,
    "cycomachead": true,
    "jyounce": true,
    "cestrensem": true,
    "bpatel": true,
    "adamkdean": true,
    "andriecool": true,
    "donvercety": true,
    "xgheaven": true,
    "amaynut": true,
    "variousmilkshakes": true,
    "avdons": true,
    "xiaokaike": true,
    "gerst20051": true,
    "joshuabriter": true,
    "temoto-kun": true,
    "abonventre": true,
    "grantgeorge": true,
    "aquiandres": true,
    "battlemidget": true,
    "warjiang": true,
    "xzycn": true,
    "maskedcoder": true,
    "bernardhamann": true,
    "maninbucket": true,
    "h0ward": true,
    "matiasmarani": true,
    "vishwasc": true,
    "pensierinmusica": true,
    "codeprowong": true,
    "reergymerej": true,
    "coleww": true,
    "pdedkov": true,
    "edwin_estrada": true,
    "sammyteahan": true,
    "lova": true,
    "jackvial": true,
    "linuxwizard": true,
    "wkaifang": true,
    "keanodejs": true,
    "shikloshi": true,
    "helsner": true,
    "draganhr": true,
    "gamr": true,
    "necr0": true,
    "panoptican": true,
    "leodutra": true,
    "temsa": true,
    "raisiqueira": true,
    "raelgor": true,
    "elussich": true,
    "pandao": true,
    "jonathanbergson": true,
    "kikna": true,
    "rakeshalhan": true,
    "dongxu": true,
    "josejaguirre": true,
    "clisun": true,
    "wynfrith": true,
    "zguillez": true,
    "nmccready": true,
    "redmonkeydf": true,
    "hibrahimsafak": true,
    "richardcfelix": true,
    "leahcimic": true,
    "cfleschhut": true,
    "sparkrico": true,
    "shushanfx": true,
    "kaveh.ghaboosi": true,
    "michaeldegroot": true,
    "novalu": true,
    "alexg53090": true,
    "lotfire.dev": true,
    "hacksalot": true,
    "vutran": true,
    "adritek": true,
    "prestorondo": true,
    "xunnamius": true,
    "fistynuts": true,
    "bruinebeer": true,
    "nonemoticoner": true,
    "yyscamper": true,
    "demod": true,
    "egantz": true,
    "bjmin": true,
    "qddegtya": true,
    "onbjerg": true,
    "zechau": true,
    "garenyondem": true,
    "artem_m": true,
    "nicomf1982": true,
    "zaggen": true,
    "io2work": true,
    "artjacob": true,
    "myxvisual": true,
    "deneboulton": true,
    "52u": true,
    "dorianamouroux": true,
    "yoksel": true,
    "leadfast": true,
    "benpptung": true,
    "ajduke": true,
    "tht13": true,
    "darkwark": true,
    "jakedetels": true,
    "potnox": true,
    "jonoco": true,
    "nescio": true,
    "guoer": true,
    "ifeature": true,
    "zithan": true,
    "micromax720": true,
    "holly": true,
    "qlqllu": true,
    "schwartzman": true,
    "nsmithau": true,
    "baiang": true,
    "pablo.tavarez": true,
    "sobralia": true,
    "heyimeugene": true,
    "andrewtimney": true,
    "blackkoi0606": true,
    "kagawa": true,
    "arielfr": true,
    "pmasa": true,
    "kirkhammetz": true,
    "hongbo-miao": true,
    "theoryofnekomata": true,
    "scytalezero": true,
    "windqyoung": true,
    "mark24code": true,
    "x0000ff": true,
    "surfacew": true,
    "edision": true,
    "hingsir": true,
    "wezhang": true,
    "studi11": true,
    "zwxajh": true,
    "ghostcode521": true,
    "antixrist": true,
    "jungae1000": true,
    "apopek": true,
    "aprilchen": true,
    "sfabrizio": true,
    "happywang": true,
    "szymex73": true,
    "peunzhang": true,
    "supnate": true,
    "chrisx": true,
    "blade254353074": true,
    "freaktechnik": true,
    "shakakira": true,
    "neo1": true,
    "scottfreecode": true,
    "stone_breaker": true,
    "boogy": true,
    "knoja4": true,
    "tmurngon": true,
    "degouville": true,
    "sqrtthree": true,
    "mikestaub": true,
    "meetravi": true,
    "ognjen.jevremovic": true,
    "azevedo": true,
    "morogasper": true,
    "erniep888": true,
    "vaju": true,
    "xrush": true,
    "esenor": true,
    "ahvonenj": true,
    "tedyhy": true,
    "froguard": true,
    "dmandola11": true,
    "iori20091101": true,
    "classicoldsong": true,
    "rylan_yan": true,
    "filipesoccol": true,
    "rangzf": true,
    "ferchoriverar": true,
    "qk4": true,
    "vur": true,
    "anoubis": true,
    "aidenzou": true,
    "tamer1an": true,
    "mseminatore": true,
    "joaquin.briceno": true,
    "yuch4n": true,
    "cblumer": true,
    "piecioshka": true,
    "sopepos": true,
    "brainpoint": true,
    "shrimpseaweed": true,
    "tin-lek": true,
    "chinawolf_wyp": true,
    "steakeye": true,
    "junos": true,
    "chrisakakay": true,
    "tahark": true,
    "zoxon": true,
    "jaguarj": true,
    "8code": true,
    "arsari": true,
    "princetoad": true,
    "jaxcode": true,
    "rocket0191": true,
    "playthefallen": true,
    "latinosoft": true,
    "abetomo": true,
    "jakedalus": true,
    "sfgarza": true,
    "shuoshubao": true,
    "alanerzhao": true,
    "ironclad.soul": true,
    "stephencorwin": true,
    "ys_sidson_aidson": true,
    "sibawite": true,
    "vehbiemiroglu": true,
    "heartnett": true,
    "dxdspirits": true,
    "maxlevs": true,
    "panlw": true,
    "ljmf00": true,
    "metaa": true,
    "ansonhorse": true,
    "solzimer": true,
    "huarse": true,
    "jamesallured": true,
    "madsummer": true,
    "blog": true,
    "jiang-xuan": true,
    "0x9r3ydu5": true,
    "vb078": true,
    "tangweikun": true,
    "eirikbirkeland": true,
    "thangakumar": true,
    "hkgsherlock": true,
    "bifuer": true,
    "kodekracker": true,
    "rfortune": true,
    "mordenius": true,
    "sendypw": true,
    "noccer": true,
    "kevin-wynn": true,
    "highgravity": true,
    "wesleylhandy": true,
    "xfloops": true,
    "swedendrift": true,
    "phil1929": true,
    "mahamdani": true,
    "shoresh319": true,
    "korooney": true,
    "touskar": true,
    "hummatli": true,
    "kontrax": true,
    "soenkekluth": true,
    "ianpaschal": true,
    "456wyc": true,
    "qaisaboujaoude": true,
    "geassor": true,
    "nraibaud": true,
    "youcp": true,
    "iceriver2": true,
    "losymear": true,
    "bouchezb": true,
    "sternelee": true,
    "imaginegenesis": true,
    "yepzy": true,
    "berkmann18": true,
    "ryanlittle": true,
    "evert-arias": true,
    "alandu": true,
    "zenfeder": true,
    "ohom": true,
    "rubiadias": true,
    "cosmin.vasilache": true,
    "ezeikel": true,
    "gpmetheny": true,
    "zuosh": true,
    "crwnvr": true,
    "tranceyos2419": true,
    "avivharuzi": true,
    "tooyond": true,
    "gux": true,
    "xiaobing": true,
    "milesq": true,
    "aleivc": true
  },
  "readmeFilename": "README.md",
  "homepage": "https://github.com/Marak/colors.js",
  "keywords": [
    "ansi",
    "terminal",
    "colors"
  ],
  "bugs": {
    "url": "https://github.com/Marak/colors.js/issues"
  },
  "license": "MIT",
  "contributors": [
    "DABH (https://github.com/DABH)"
  ],
  "version": "1.3.3",
  "scripts": {
    "lint": "eslint . --fix",
    "test": "node tests/basic-test.js && node tests/safe-test.js"
  },
  "engines": {
    "node": ">=0.1.90"
  },
  "main": "lib/index.js",
  "devDependencies": {
    "eslint": "^5.2.0",
    "eslint-config-google": "^0.11.0"
  },
  "gitHead": "b63ef88e521b42920a9e908848de340b31e68c9d",
  "dist": {
    "integrity": "sha512-mmGt/1pZqYRjMxB1axhTo16/snVZ5krrKkcmMeVKxzECMMXoCgnvTPp10QgHfcbQZw8Dq2jMNG6je4JlWU0gWg==",
    "shasum": "39e005d546afe01e01f9c4ca8fa50f686a01205d",
    "tarball": "https://registry.npmjs.org/colors/-/colors-1.3.3.tgz",
    "fileCount": 21,
    "unpackedSize": 37746,
    "npm-signature": "-----BEGIN PGP SIGNATURE-----\r\nVersion: OpenPGP.js v3.0.4\r\nComment: https://openpgpjs.org\r\n\r\nwsFcBAEBCAAQBQJcDcL1CRA9TVsSAnZWagAAZhMP/RLpT/dg263sOTxYH3sF\ntwWPJmzlEg73lve6fi5la0FMcrt5qGVk+xFW3UjDtjNR4RZEvSqXkr/2lvZq\na9xr3WL0TLC83FYKNPVBX6xYR+IszHL0FmSGumLArPO+fnp1r96w9S4ZqWUd\n1In1tZZwqr79u+1r1y5zgS2XVDKmSi3G176b1dIwmT0rN6wtMq31gka9EMJg\ntlSRpPjJLB51MJZFMubAxVVUvTo1Xof5232r/0vtVeD5lQmC24YW5Oo3Yf8Y\n2gXtaE6t0K1w4pCCU9sYGuDIVcBiPQsZsOcFnLivSh1v+L9YpbyRSLnPO+pL\nj996D9sLMGUaInnDyR2hU1pAuw4gJkKWCIKpHXmMf7eJTTAO9co0PkHRVPyz\nmgv34r1NJyuFncj/fZ/WVKrSp68y0YsFckciMzvsEQXrz4SHMTng0yYQbp1W\n4XDSMxVbLRUNizN7B0J+q8KLzmirKg1xzSjeRrLXAdAhVZXk1nCGCMkpCBa7\ndUQRV5MK6XRi50DKgVdKQuGl95NxqJqmYDauT2xG1PB2rlHKZtMsYo74BXH9\nzzrmQ1QiDWp9BVi6bzZmJnPzwBfUQV6M0bQ1x8txXOHso0hoEILXCrcrGeK7\nfzlysIUd9VNy5H0gVQa3XPB66N0G3bHacDT/inDxXp3MFLz/6S/q43g9JO8w\n6FqR\r\n=mC+K\r\n-----END PGP SIGNATURE-----\r\n"
  },
  "directories": {}
}
