{
  "name": "mem",
  "description": "Memoize functions - An optimization used to speed up consecutive function calls by caching the result of calls with identical input",
  "dist-tags": {
    "latest": "5.1.0"
  },
  "versions": [
    "0.1.0",
    "0.1.1",
    "1.0.0",
    "1.1.0",
    "2.0.0",
    "3.0.0",
    "3.0.1",
    "4.0.0",
    "4.1.0",
    "4.2.0",
    "4.3.0",
    "5.0.0",
    "5.1.0"
  ],
  "maintainers": [
    "sindresorhus <sindresorhus@gmail.com>"
  ],
  "time": {
    "modified": "2019-06-15T13:14:40.046Z",
    "created": "2013-01-22T23:16:13.120Z",
    "0.0.1": "2013-01-22T23:16:15.354Z",
    "0.1.0": "2015-12-21T18:44:14.279Z",
    "0.1.1": "2016-02-02T15:53:17.433Z",
    "1.0.0": "2016-10-19T17:34:31.486Z",
    "1.1.0": "2016-10-19T18:05:26.119Z",
    "2.0.0": "2017-09-25T06:32:08.213Z",
    "3.0.0": "2017-10-11T15:56:14.080Z",
    "3.0.1": "2018-06-20T06:38:02.452Z",
    "4.0.0": "2018-08-27T17:33:38.386Z",
    "4.1.0": "2019-01-30T08:45:27.864Z",
    "4.2.0": "2019-03-12T17:41:47.237Z",
    "4.3.0": "2019-03-31T19:09:03.906Z",
    "5.0.0": "2019-05-17T17:25:34.041Z",
    "5.1.0": "2019-06-15T13:14:37.532Z"
  },
  "author": "Sindre Sorhus <sindresorhus@gmail.com> (sindresorhus.com)",
  "repository": {
    "type": "git",
    "url": "git+https://github.com/sindresorhus/mem.git"
  },
  "keywords": [
    "memoize",
    "function",
    "mem",
    "memoization",
    "cache",
    "caching",
    "optimize",
    "performance",
    "ttl",
    "expire",
    "promise"
  ],
  "readmeFilename": "readme.md",
  "homepage": "https://github.com/sindresorhus/mem#readme",
  "bugs": {
    "url": "https://github.com/sindresorhus/mem/issues"
  },
  "license": "MIT",
  "users": {
    "antixrist": true,
    "psychollama": true,
    "quocnguyen": true,
    "sasquatch": true,
    "joelwallis": true,
    "pldin601": true,
    "cr8tiv": true,
    "daniel-zahariev": true,
    "xch": true
  },
  "version": "5.1.0",
  "engines": {
    "node": ">=8"
  },
  "scripts": {
    "test": "xo && ava && tsd"
  },
  "dependencies": {
    "map-age-cleaner": "^0.1.3",
    "mimic-fn": "^2.1.0",
    "p-is-promise": "^2.1.0"
  },
  "devDependencies": {
    "ava": "^1.4.1",
    "delay": "^4.1.0",
    "tsd": "^0.7.3",
    "xo": "^0.24.0"
  },
  "gitHead": "ce7f3b7135e32d80877dedf0f0b7bd3e14d0ad91",
  "dist": {
    "integrity": "sha512-9egM8rCo4wKiKuTwK1nFlSk39HbgluK93EgUmmboF85CVuKp7PoAwK3C8krkJeeFiH/ltExwVxcu+i2dKZYtDw==",
    "shasum": "b94ee9b888d26928dd9d91cab107fa04b925730b",
    "tarball": "https://registry.npmjs.org/mem/-/mem-5.1.0.tgz",
    "fileCount": 5,
    "unpackedSize": 9692,
    "npm-signature": "-----BEGIN PGP SIGNATURE-----\r\nVersion: OpenPGP.js v3.0.4\r\nComment: https://openpgpjs.org\r\n\r\nwsFcBAEBCAAQBQJdBO8+CRA9TVsSAnZWagAAYMIP/AqXJioq5I4sVO2IxRoB\nMVQEq8bieSUTDz33I3/J/3qhv8yDAzs6AqpqPtk4uSHwB9ze3LHkV8kPsv6m\nnMFddbVGs8Df7vAaxkuH6XdXiZmnx3QCSqA/a5hjTwuPKsd0qYnTsId6NyVo\nbhXrL8mR0AUQ0+KihQiAu9cjXKFSh32QeKqRR7/wmZ5Y2q06a9OsSd8BMlzW\nIAD/0PqjfNkb1LWmeJk6uXd8/N6Mk4Sd8INY/QdE2JaQac/aTsu7FM5r8J+z\n5aqpvlXdj7HVWs+cxsCw5W/VMybpsEgb7cCS9TPFvkZ8A0+5dGaKhE+xGkoG\nhMqnKtSGtB9voaZhiQYO7m1P1h+OrUM9nKosvgGA6+yhP4k/dXGjBgwS/+Bc\nzuArX4LrWIyV7cCu2JyqYWJHf+VFpgVgoSHG4jKvE0lyZ9pqsGuqGNeWqj62\nLkhrB+4s06cWlNI7ozWldgYVFrbjM4TEcQm8DHD4CXtoo9SifnbsSWbI+nmA\nyEUVAxLov3uYSpaOgwEWRomnT7Gk27Hx2wDR3TxI8TRdAnDoi3DK93Jjln45\nwjBYRkx7BGBTAecH5S3PxI7XmB0Y1RnihNAtPu9KInjG+VNLTFqHihUB24FE\nsxpoI157vi99gkDJdxsiVDWN9JZ3gdz7+3tCIYsJz5j+R4FjLKAWf6QOeHz5\n/2IV\r\n=ozSS\r\n-----END PGP SIGNATURE-----\r\n"
  },
  "directories": {}
}
